swole/__init__.py
swole/core/__init__.py
swole/core/ajax.py
swole/core/application.py
swole/core/page.py
swole/core/utils.py
swole/skins/__init__.py
swole/skins/base.css
swole/skins/skin.py
swole/widgets/__init__.py
swole/widgets/base.py
swole/widgets/button.py
swole/widgets/header.py
swole/widgets/input.py
swole/widgets/markdown.py
swole-0.0.4.dist-info/METADATA
swole-0.0.4.dist-info/WHEEL
swole-0.0.4.dist-info/top_level.txt
swole-0.0.4.dist-info/RECORD
