Metadata-Version: 2.1
Name: swole
Version: 0.0.4
Summary: Streamlit, but better.
Home-page: https://github.com/astariul/swole
Author: Nicolas REMOND
Author-email: remondnicola@gmail.com
License: UNKNOWN
Platform: UNKNOWN
Classifier: Programming Language :: Python :: 3.6
Classifier: Operating System :: OS Independent
Requires-Python: >=3.6
Requires-Dist: dominate (==2.5.2)
Requires-Dist: fastapi (==0.61.1)
Requires-Dist: uvicorn (==0.11.8)
Requires-Dist: aiofiles (==0.5.0)
